attrdict/__init__.py
attrdict/default.py
attrdict/dictionary.py
attrdict/mapping.py
attrdict/merge.py
attrdict/mixins.py
gattrdict-2.0.1.dist-info/LICENSE.txt
gattrdict-2.0.1.dist-info/METADATA
gattrdict-2.0.1.dist-info/WHEEL
gattrdict-2.0.1.dist-info/top_level.txt
gattrdict-2.0.1.dist-info/zip-safe
gattrdict-2.0.1.dist-info/RECORD
