Metadata-Version: 2.1
Name: gattrdict
Version: 2.0.1
Summary: A dict with attribute-style access
Home-page: https://github.com/CreatorZZY/gAttrDict.git
Author: Brendan Curran-Johnson; George Zhao
Author-email: brendan@bcjbcj.ca
License: MIT License
Classifier: Development Status :: 7 - Inactive
Classifier: Intended Audience :: Developers
Classifier: License :: OSI Approved :: MIT License
Classifier: Programming Language :: Python :: 2
Classifier: Programming Language :: Python :: 2.7
Classifier: Programming Language :: Python :: 3
Classifier: Programming Language :: Python :: Implementation :: CPython
Classifier: Programming Language :: Python :: Implementation :: PyPy
License-File: LICENSE.txt
Requires-Dist: six
